ot_handler/__init__.py
ot_handler/liquid_handler.py
ot_handler-0.2.0.dist-info/licenses/LICENSE
ot_handler-0.2.0.dist-info/METADATA
ot_handler-0.2.0.dist-info/WHEEL
ot_handler-0.2.0.dist-info/top_level.txt
ot_handler-0.2.0.dist-info/RECORD
