Metadata-Version: 2.4
Name: ot_handler
Version: 0.2.0
Summary: A comprehensive solution for automating liquid handling tasks on the Opentrons OT-2.
Home-page: https://github.com/BIIE-DeepIR/ot-handler
Author: Oskari Vinko
Author-email: oskari.vinko@immune.engineering
Classifier: Programming Language :: Python :: 3
Classifier: License :: OSI Approved :: MIT License
Classifier: Operating System :: OS Independent
Requires-Python: >=3.10
License-File: LICENSE
Requires-Dist: opentrons==8.2.0
Dynamic: author
Dynamic: author-email
Dynamic: classifier
Dynamic: description
Dynamic: description-content-type
Dynamic: home-page
Dynamic: license-file
Dynamic: requires-dist
Dynamic: requires-python
Dynamic: summary
